{
	"node": "n8n-nodes-base.youTube",
	"nodeVersion": "1.0",
	"codexVersion": "1.0",
	"categories": ["Marketing & Content"],
	"resources": {
		"credentialDocumentation": [
			{
				"url": "https://docs.quicksales.vn/integrations/builtin/credentials/google/oauth-single-service/"
			}
		],
		"primaryDocumentation": [
			{
				"url": "https://docs.quicksales.vn/integrations/builtin/app-nodes/n8n-nodes-base.youtube/"
			}
		],
		"generic": [
			{
				"label": "Using Automation to Boost Productivity in the Workplace",
				"icon": "💪",
				"url": "https://quicksales.vn/blog/using-automation-to-boost-productivity-in-the-workplace/"
			}
		]
	}
}
